{
  "kind": "collectionType",
  "collectionName": "orders",
  "info": {
    "singularName": "order",
    "pluralName": "orders",
    "displayName": "Order",
    "description": ""
  },
  "options": {
    "draftAndPublish": true
  },
  "pluginOptions": {},
  "attributes": {
    "amount": {
      "type": "float"
    },
    "name": {
      "type": "string"
    },
    "email": {
      "type": "string"
    },
    "address": {
      "type": "string"
    },
    "dishes": {
      "type": "json"
    },
    "phone_number": {
      "type": "string"
    }
  }
}
